[
  {
    "url": "img/Epcot100.JPG",
    "caption": "The Frozen Ride"
  },
  {
    "url": "img/Epcot101.jpeg",
    "caption": "Photpass Magic Shot - Entrance to Epcot"
  },
  {
    "url": "img/Epcot102.jpeg",
    "caption": "China in World Showcase"
  },
  {
    "url": "img/Epcot103.jpeg",
    "caption": "Imagination Pavillion - Epcot"
  },
  {
    "url": "img/Epcot104.JPG",
    "caption": "LA Cava Tequila Bar - Epcot"
  },
  {
    "url": "img/Epcot105.JPEG",
    "caption": "Figment - Imagination Pavillion"
  },
  {
    "url": "img/Epcot106.JPG",
    "caption": "Epcot Food and Wine Festival"
  },
  {
    "url": "img/Epcot107.jpeg",
    "caption": "Festival of the Holidays"
  },
  {
    "url": "img/Epcot108.JPG",
    "caption": "Epcot Fireworks"
  }
]